Workbook

Sheet README
A1: SKYHOOK PROGRAM — FINANCIAL MODEL v1 (Rule 4: base case = Conservative only)
A3: Sheets: Assumptions (blue = change me) · Design Calcs (physics, EQ 1-5) · Phase Budgets · Cash Flow & Payback.
A4: Color code: BLUE = hardcoded inputs · BLACK = formulas · GREEN = cross-sheet links · YELLOW fill = key assumption needing attention.
A5: All performance formulas trace to the project instructions: Tsiolkovsky (EQ 1), kinematics (EQ 2-3), taper & Moravec/Forward mass ratio (EQ 4), ED reboost energy (EQ 5).
A6: Sources: Moravec 1977; Hoyt & Forward HASTOL reports; NASA MXER studies; project instructions Rev A (Parts VI-VII). Anchors, not promises.
A7: Scenario selector on Cash Flow sheet drives the whole model: Conservative / Baseline / Optimistic.

Sheet Assumptions
A1: LADDER ASSUMPTIONS (Rule 4)
A2: Parameter | B2: Conservative | C2: Baseline | D2: Optimistic | E2: Source / note
A3: Fiber strength retention (1 - derate); joints/weave/aging | B3: 0.7 | C3: 0.85 | D3: 1 | E3: Rev A ladder = rev_a.json derate_fraction 30%/15%/0%; Conservative is Rule 4 base case
A4: Ascent losses (m/s) | B4: 1800 | C4: 1500 | D4: 1200 | E4: gravity+drag for suborbital profile
A5: Launch price during construction ($/kg) | B5: 2500 | C5: 1500 | D5: 800 | E5: blended commercial, Part 7.2
A6: Power chain efficiency (ED reboost) | B6: 0.15 | C6: 0.2 | D6: 0.3 | E6: array->PMAD->thrust, MXER studies
A7: Electricity cost ($/kWh, amortized array) | B7: 0.08 | C7: 0.06 | D7: 0.04 | E7: labeled assumption
A8: Ops + wear + insurance increment ($/kg) | B8: 12 | C8: 8 | D8: 5 | E8: labeled assumption pending subsystem estimates
A9: Hardware mass factor (x tether launch cost) | B9: 1.8 | C9: 1.6 | D9: 1.4 | E9: hub/arrays/tips, Part 7.2
A10: Boost price to customer ($/kg) | B10: 500 | C10: 500 | D10: 500 | E10: held flat across scenarios deliberately
A11: Mature cadence (catches/day) | B11: 1 | C11: 2 | D11: 3 | E11: Part 7.3
A12: Payload per catch (kg) | B12: 5000 | C12: 5000 | D12: 5000 | E12: Phase 3 reference
A13: Revenue ramp Y1/Y2/Y3 of ops | B13: 0.3 | C13: 0.4 | D13: 0.5 | E13: fraction of mature in first ops year
A14: Fixed annual ops cost ($M) | B14: 80 | C14: 60 | D14: 45 | E14: mission ops, ground, G&A
... A16: Program + launcher fleet capex ($M) | B16: 6000 | C16: 5000 | D16: 4000 | E16: Part 7.2: fleet ~$2-3B + program/reserves; conservative adds margin
A17: SHARED DESIGN POINT (Rev A, 2.5 km/s GTO/high-elliptical reference)
A18: Parameter | B18: Value | E18: Source / note
A19: CoM altitude (km) | B19: 610 | E19: Zylon baseline, Part 2.3 table
A20: Half-length L (km) | B20: 320
A21: Rev A reference tip speed (km/s) — GTO/high-elliptical | B21: 2.5
A22: Safety factor on stress | B22: 2.5
A23: Fiber tensile strength sigma (GPa) | B23: 5.8
A24: Fiber density rho (kg/m3) | B24: 1560
A25: Vehicle exhaust velocity (km/s) | B25: 3.4
A26: All-rocket reference dv (km/s) | B26: 9.4
A27: Structure fraction of vehicle | B27: 0.04
A28: Equatorial rotation help (km/s) | B28: 0.465
A31: PHYSICAL CONSTANTS
A32: mu Earth (km3/s2) | B32: 398600
A33: Earth radius (km) | B33: 6371

Sheet Design Calcs
A1: DESIGN CALCS — all formulas, per scenario (EQ 1-5)
A2: Quantity | B2: Conservative | C2: Baseline | D2: Optimistic | E2: Formula trace
A3: Orbital radius R (km) | B3: =Assumptions!$B$33+Assumptions!$B$19 -> 6981 | C3: =Assumptions!$B$33+Assumptions!$B$19 -> 6981 | D3: =Assumptions!$B$33+Assumptions!$B$19 -> 6981 | E3: R = R_E + h
A4: Orbital velocity v_orb (km/s) | B4: =SQRT(Assumptions!$B$32/B3) -> 7.5563111 | C4: =SQRT(Assumptions!$B$32/C3) -> 7.5563111 | D4: =SQRT(Assumptions!$B$32/D3) -> 7.5563111 | E4: EQ 2
A5: Spin rate omega (rad/s) | B5: =Assumptions!B15/Assumptions!$B$20 -> 0.0078125 | C5: =Assumptions!C15/Assumptions!$B$20 -> 0.0078125 | D5: =Assumptions!D15/Assumptions!$B$20 -> 0.0078125 | E5: omega = v_tip/L
A6: Rotation period (min) | B6: =2*PI()/B5/60 -> 13.404129 | C6: =2*PI()/C5/60 -> 13.404129 | D6: =2*PI()/D5/60 -> 13.404129 | E6: 2pi/omega
A7: Tip acceleration (g) | B7: =Assumptions!B15^2*1000/Assumptions!$B$20/9.81 -> 1.9909531 | C7: =Assumptions!C15^2*1000/Assumptions!$B$20/9.81 -> 1.9909531 | D7: =Assumptions!D15^2*1000/Assumptions!$B$20/9.81 -> 1.9909531 | E7: v^2/L
A8: Derated char. velocity V_c (km/s) | B8: =SQRT(2*Assumptions!$B$23*1000000000*Assumptions!B3/Assumptions!$B$24)/1000 -> 2.281475 | C8: =SQRT(2*Assumptions!$B$23*1000000000*Assumptions!C3/Assumptions!$B$24)/1000 -> 2.514063 | D8: =SQRT(2*Assumptions!$B$23*1000000000*Assumptions!D3/Assumptions!$B$24)/1000 -> 2.7268842 | E8: EQ 4 with ladder derate
A9: Working ratio x = v_tip/(V_c/sqrt(SF)) | B9: =Assumptions!B15/(B8/SQRT(Assumptions!$B$22)) -> 1.732584 | C9: =Assumptions!C15/(C8/SQRT(Assumptions!$B$22)) -> 1.5722944 | D9: =Assumptions!D15/(D8/SQRT(Assumptions!$B$22)) -> 1.4495838 | E9: EQ 4
A10: Taper ratio | B10: =EXP(B9^2) -> 20.122675 | C10: =EXP(C9^2) -> 11.847413 | D10: =EXP(D9^2) -> 8.1767364 | E10: exp(x^2)
A11: Tether/payload mass ratio (single arm) | B11: =SQRT(PI())*B9*EXP(B9^2)*ERF(B9) -> 60.913043 | C11: =SQRT(PI())*C9*EXP(C9^2)*ERF(C9) -> 32.152287 | D11: =SQRT(PI())*D9*EXP(D9^2)*ERF(D9) -> 20.160696 | E11: Moravec/Forward
A12: Total tether mass, 2 arms (t) | B12: =2*B11*Assumptions!B12/1000 -> 609.13043 | C12: =2*C11*Assumptions!C12/1000 -> 321.52287 | D12: =2*D11*Assumptions!D12/1000 -> 201.60696 | E12: x payload per catch
A13: Catch speed ground-rel (km/s) | B13: =B4-Assumptions!B15-Assumptions!$B$28 -> 4.5913111 | C13: =C4-Assumptions!C15-Assumptions!$B$28 -> 4.5913111 | D13: =D4-Assumptions!D15-Assumptions!$B$28 -> 4.5913111 | E13: EQ 3 + Earth help
A14: Vehicle dv incl losses (km/s) | B14: =B13+Assumptions!B4/1000 -> 6.3913111 | C14: =C13+Assumptions!C4/1000 -> 6.0913111 | D14: =D13+Assumptions!D4/1000 -> 5.7913111 | E14: ladder losses
A15: dv saved vs all-rocket (km/s) | B15: =Assumptions!$B$26-B14 -> 3.0086889 | C15: =Assumptions!$B$26-C14 -> 3.3086889 | D15: =Assumptions!$B$26-D14 -> 3.6086889
A16: Payload fraction w/ skyhook | B16: =MAX(0,EXP(-B14/Assumptions!$B$25)-Assumptions!$B$27) -> 0.11262103 | C16: =MAX(0,EXP(-C14/Assumptions!$B$25)-Assumptions!$B$27) -> 0.12669957 | D16: =MAX(0,EXP(-D14/Assumptions!$B$25)-Assumptions!$B$27) -> 0.14207678 | E16: EQ 1 - structure
A17: Payload fraction all-rocket | B17: =MAX(0,EXP(-Assumptions!$B$26/Assumptions!$B$25)-Assumptions!$B$27) -> 0.022994624 | C17: =MAX(0,EXP(-Assumptions!$B$26/Assumptions!$B$25)-Assumptions!$B$27) -> 0.022994624 | D17: =MAX(0,EXP(-Assumptions!$B$26/Assumptions!$B$25)-Assumptions!$B$27) -> 0.022994624 | E17: EQ 1
A18: Payload multiplier (x) | B18: =IF(B17>0,B16/B17,"inf") -> 4.8977111 | C18: =IF(C17>0,C16/C17,"inf") -> 5.5099647 | D18: =IF(D17>0,D16/D17,"inf") -> 6.1786956
A19: System capex: launch+hardware ($M) | B19: =B12*1000*Assumptions!B5*Assumptions!B9/1000000 -> 2741.087 | C19: =C12*1000*Assumptions!C5*Assumptions!C9/1000000 -> 771.6549 | D19: =D12*1000*Assumptions!D5*Assumptions!D9/1000000 -> 225.79979 | E19: tether t x $/kg x hw factor
A20: Reboost energy per kg (MJ) | B20: =2*B4*Assumptions!B15 -> 37.781555 | C20: =2*C4*Assumptions!C15 -> 37.781555 | D20: =2*D4*Assumptions!D15 -> 37.781555 | E20: EQ 5 momentum view: 2 v_orb v_tip
A21: Electricity per boosted kg ($) | B21: =B20/Assumptions!B6/3.6*Assumptions!B7 -> 5.5972675 | C21: =C20/Assumptions!C6/3.6*Assumptions!C7 -> 3.1484629 | D21: =D20/Assumptions!D6/3.6*Assumptions!D7 -> 1.3993169 | E21: MJ/eff -> kWh x $/kWh
A22: Marginal cost ($/kg) | B22: =B21+Assumptions!B8 -> 17.597267 | C22: =C21+Assumptions!C8 -> 11.148463 | D22: =D21+Assumptions!D8 -> 6.3993169 | E22: + ops/wear
A23: Annual upmass (t/yr) | B23: =Assumptions!B11*365*Assumptions!B12/1000 -> 1825 | C23: =Assumptions!C11*365*Assumptions!C12/1000 -> 3650 | D23: =Assumptions!D11*365*Assumptions!D12/1000 -> 5475 | E23: cadence x payload
A24: Annual revenue at maturity ($M) | B24: =B23*1000*Assumptions!B10/1000000 -> 912.5 | C24: =C23*1000*Assumptions!C10/1000000 -> 1825 | D24: =D23*1000*Assumptions!D10/1000000 -> 2737.5
A25: Annual marginal cost ($M) | B25: =B23*1000*B22/1000000 -> 32.115013 | C25: =C23*1000*C22/1000000 -> 40.69189 | D25: =D23*1000*D22/1000000 -> 35.03626
A27: ERF AUDIT — Abramowitz & Stegun 7.1.26 rational approximation, cross-check only | E27: Mass ratio (row 11) uses Excel's native ERF(); this block validates it independently
A28: t = 1/(1+p*x), p=0.3275911 | B28: =1/(1+0.3275911*B9) -> 0.63792634 | C28: =1/(1+0.3275911*C9) -> 0.66003567 | D28: =1/(1+0.3275911*D9) -> 0.67802552 | E28: A&S 7.1.26 substitution
A29: erf(x) approx (A&S 7.1.26 polynomial) | B29: =1-(0.254829592*B28-0.284496736*B28^2+1.421413741*B28^3-1.453152027*B28^4+1.061405429*B28^5)*EXP(-B9^2) -> -4.7806514 | C29: =1-(0.254829592*C28-0.284496736*C28^2+1.421413741*C28^3-1.453152027*C28^4+1.061405429*C28^5)*EXP(-C9^2) -> -2.6743718 | D29: =1-(0.254829592*D28-0.284496736*D28^2+1.421413741*D28^3-1.453152027*D28^4+1.061405429*D28^5)*EXP(-D9^2) -> -1.6985801 | E29: max abs error 1.5e-7 per A&S
A30: erf(x) native (Excel ERF) | B30: =ERF(B9) -> 0.98572405 | C30: =ERF(C9) -> 0.97382194 | D30: =ERF(D9) -> 0.95963762 | E30: cross-check reference
A31: Approximation error (abs) | B31: =ABS(B29-B30) -> 5.7663754 | C31: =ABS(C29-C30) -> 3.6481938 | D31: =ABS(D29-D30) -> 2.6582177 | E31: should be < 2e-7

Sheet Phase Budgets
A1: PHASE BUDGETS (Part VI) — $M
A2: Phase | B2: Low ($M) | C2: High ($M) | D2: Exit criteria / notes
A3: Phase 0 — Foundations (Y0-2) | B3: 10 | C3: 30 | D3: Digital twin validated; joint statistics; capture demo; regulatory groundwork
A4: Phase 1 — Orbital demos (Y2-5) | B4: 60 | C4: 150 | D4: Repeated catch/throw on orbit; first deorbit revenue; ledger closed by ED
A5: Phase 2 — Lariat (Y5-10) | B5: 1000 | C5: 3000 | D5: Positive operating cash flow; >100 commercial exchanges; insurance record
A6: Phase 3 — Mainline (Y10-18) | B6: 10000 | C6: 11000 | D6: <$300/kg marginal; daily cadence; largely internally financed
A7: Cumulative program (low/high) | B7: =SUM(B3:B6) -> 11070 | C7: =SUM(C3:C6) -> 14180

Sheet Cash Flow & Payback
A1: CASH FLOW & PAYBACK — Rev A reference (scenario-driven)
A2: Scenario selector (type exactly): | B2: Conservative | C2: Conservative / Baseline / Optimistic
A3: Scenario column index | B3: =MATCH(B2,{"Conservative","Baseline","Optimistic"},0)+1 -> 2
A4: Total capex: system + program/fleet ($M) | B4: =INDEX('Design Calcs'!19:19,B3)+INDEX(Assumptions!16:16,B3) -> 8741.087
A5: Mature revenue ($M/yr) | B5: =INDEX('Design Calcs'!24:24,B3) -> 912.5
A6: Mature marginal cost ($M/yr) | B6: =INDEX('Design Calcs'!25:25,B3) -> 32.115013
A7: Fixed ops ($M/yr) | B7: =INDEX(Assumptions!14:14,B3) -> 80
A8: Ramp Y1 of ops | B8: =INDEX(Assumptions!13:13,B3) -> 0.3
A10: Year | B10: 1 | C10: 2 | D10: 3 | E10: 4 | F10: 5 | G10: 6 | H10: 7 | I10: 8 | J10: 9 | K10: 10 | L10: 11 | M10: 12 | N10: 13 | O10: 14 | P10: 15
A11: Capex spend ($M) | B11: =$B$4*0.15 -> 1311.163 | C11: =$B$4*0.3 -> 2622.3261 | D11: =$B$4*0.35 -> 3059.3804 | E11: =$B$4*0.2 -> 1748.2174 | F11: 0 | G11: 0 | H11: 0 | I11: 0 | J11: 0 | K11: 0 | L11: 0 | M11: 0 | N11: 0 | O11: 0 | P11: 0
A12: Revenue ($M) | B12: 0 | C12: 0 | D12: 0 | E12: 0 | F12: =$B$5*$B$8 -> 273.75 | G12: =$B$5*MIN(1,$B$8+0.3) -> 547.5 | H12: =$B$5 -> 912.5 | I12: =$B$5 -> 912.5 | J12: =$B$5 -> 912.5 | K12: =$B$5 -> 912.5 | L12: =$B$5 -> 912.5 | M12: =$B$5 -> 912.5 | N12: =$B$5 -> 912.5 | O12: =$B$5 -> 912.5 | P12: =$B$5 -> 912.5
A13: Opex ($M) | B13: 0 | C13: 0 | D13: 0 | E13: 0 | F13: =$B$6*$B$8+$B$7 -> 89.634504 | G13: =$B$6*MIN(1,$B$8+0.3)+$B$7 -> 99.269008 | H13: =$B$6+$B$7 -> 112.11501 | I13: =$B$6+$B$7 -> 112.11501 | J13: =$B$6+$B$7 -> 112.11501 | K13: =$B$6+$B$7 -> 112.11501 | L13: =$B$6+$B$7 -> 112.11501 | M13: =$B$6+$B$7 -> 112.11501 | N13: =$B$6+$B$7 -> 112.11501 | O13: =$B$6+$B$7 -> 112.11501 | P13: =$B$6+$B$7 -> 112.11501
A14: Net cash flow ($M) | B14: =B12-B11-B13 -> -1311.163 | C14: =C12-C11-C13 -> -2622.3261 | D14: =D12-D11-D13 -> -3059.3804 | E14: =E12-E11-E13 -> -1748.2174 | F14: =F12-F11-F13 -> 184.1155 | G14: =G12-G11-G13 -> 448.23099 | H14: =H12-H11-H13 -> 800.38499 | I14: =I12-I11-I13 -> 800.38499 | ... P14: =P12-P11-P13 -> 800.38499
A15: Cumulative ($M) | B15: =B14 -> -1311.163 | C15: =B15+C14 -> -3933.4891 | D15: =C15+D14 -> -6992.8696 | E15: =D15+E14 -> -8741.087 | F15: =E15+F14 -> -8556.9715 | G15: =F15+G14 -> -8108.7405 | H15: =G15+H14 -> -7308.3555 | I15: =H15+I14 -> -6507.9705 | J15: =I15+J14 -> -5707.5855 | ... P15: =O15+P14 -> -905.27559
A16: Payback year (cumulative > 0) | B16: =IFERROR(MATCH(TRUE(),INDEX(B15:P15>0,0),0),"beyond Y15") -> beyond Y15
A18: Note: capex spread Y1-Y4 (15/30/35/20%); ops begin Y5 with revenue ramp. Includes program + launcher fleet via Assumptions row 16. Excludes Phases 0-2 (separately financed and revenue-bearing) — see Phase Budgets. Conservative scenario also spins slower (row 15), per Rule 2.3.
A19: Static snapshot (Conservative scenario) — see finance/skyhook_finance.py for the live scenario-driven model.
